{
 "entries": {
  "ux_lab:ux_lab.home:LayoutSpec.pages": {
   "provenance": {
    "exempt": "legacy-seed: band-6 port carries the shipped ordering/grouping as the seed arrangement (design-spec §9.3 confidence rule — telemetry sidecar is seeded-empty; the grouping/hub sims re-run post-telemetry)"
   },
   "value": [
    {
     "rows": [
      [
       "buttons",
       "selects",
       "modals",
       "embeds"
      ],
      [
       "components_v2",
       "pil_cards",
       "mock_studio",
       "probe_bench"
      ],
      [
       "compare"
      ]
     ]
    }
   ]
  },
  "ux_lab:ux_lab.home:PageSpec.rows": {
   "provenance": {
    "exempt": "legacy-seed: band-6 port carries the shipped ordering/grouping as the seed arrangement (design-spec §9.3 confidence rule — telemetry sidecar is seeded-empty; the grouping/hub sims re-run post-telemetry)"
   },
   "value": [
    [
     "buttons",
     "selects",
     "modals",
     "embeds"
    ],
    [
     "components_v2",
     "pil_cards",
     "mock_studio",
     "probe_bench"
    ],
    [
     "compare"
    ]
   ]
  },
  "ux_lab:ux_lab.home:PanelSpec.layout": {
   "provenance": {
    "exempt": "legacy-seed: band-6 port carries the shipped ordering/grouping as the seed arrangement (design-spec §9.3 confidence rule — telemetry sidecar is seeded-empty; the grouping/hub sims re-run post-telemetry)"
   },
   "value": {
    "pages": [
     {
      "rows": [
       [
        "buttons",
        "selects",
        "modals",
        "embeds"
       ],
       [
        "components_v2",
        "pil_cards",
        "mock_studio",
        "probe_bench"
       ],
       [
        "compare"
       ]
      ]
     }
    ]
   }
  },
  "ux_lab:uxlab:CommandSpec.help_section_order": {
   "provenance": {
    "exempt": "legacy-seed: band-6 port carries the shipped ordering/grouping as the seed arrangement (design-spec §9.3 confidence rule — telemetry sidecar is seeded-empty; the grouping/hub sims re-run post-telemetry)"
   },
   "value": 0
  }
 },
 "schema_version": 1,
 "subsystem": "ux_lab"
}
